<?xml version="1.0" encoding="UTF-8"?>
<comment version="3.0">
  <caption>Philadelphia 76ers v Toronto Raptors</caption>
  <note>TORONTO, CANADA - OCTOBER 26: P.J. Tucker #17 of the Philadelphia 76ers stands on the court against the Toronto Raptors on October 26, 2022 at the Scotiabank Arena in Toronto, Ontario, Canada. NOTE TO USER: User expressly acknowledges and agrees that, by downloading and or using this Photograph, user is consenting to the terms and conditions of the Getty Images License Agreement. Mandatory Copyright Notice: Copyright 2022 NBAE   Vaughn Ridley/NBAE via Getty Images/AFP (Photo by Vaughn Ridley / NBAE / Getty Images / Getty Images via AFP)</note>
  <place/>
  <categories>
    <category value="GettyImageRank2"/>
    <category value="nba"/>
    <category value="Vertical"/>
    <category value="SPORT"/>
    <category value="BASKETBALL"/>
  </categories>
</comment>
